sail/__init__.py
sail/__main__.py
sail/__version__.py
sail/backups.py
sail/blueprints.py
sail/cron.py
sail/database.py
sail/deploy.py
sail/domains.py
sail/misc.py
sail/profiling.py
sail/provision.py
sail/rebuild.py
sail/sftp.py
sail/ssh.py
sail/util.py
sail/blueprints/default.yaml
sail/blueprints/fail2ban.yaml
sail/blueprints/gmail-dns.yaml
sail/blueprints/mailgun-dns.yaml
sail/blueprints/mailgun.yaml
sail/blueprints/postfix.yaml
sail/blueprints/sample.yaml
sail/blueprints/site-verification.yaml
sail/blueprints/test_apt.yaml
sail/blueprints/test_commands.yaml
sail/blueprints/test_define.yaml
sail/blueprints/test_dns.yaml
sail/blueprints/test_fail2ban.yaml
sail/blueprints/test_files.yaml
sail/blueprints/test_options.yaml
sail/blueprints/test_plugins.yaml
sail/blueprints/test_themes.yaml
sail/blueprints/test_vars.yaml
sail/premium/__init__.py
sail/premium/backups.py
sail/premium/monitor.py
sail/templates/certbot.deploy.sh
sail/templates/cloud-config.yaml
sail/templates/logrotate.conf
sail/templates/mariadb.cnf
sail/templates/nginx.certbot.conf
sail/templates/nginx.main.conf
sail/templates/nginx.main.premium.conf
sail/templates/nginx.premium.conf
sail/templates/nginx.server.conf
sail/templates/nginx.shared.conf
sail/templates/php.ini
sail/templates/premium.php
sail/templates/prepend.php
sail/templates/fail2ban/0-sail-auth-syslog.php
sail/templates/fail2ban/jail.local
sail/templates/fail2ban/nginx-deny.conf
sail/templates/fail2ban/wordpress-auth.conf
sail/templates/fail2ban/wordpress-pingback.conf
sail/templates/postfix/1-sail-mail-from.php
sail/templates/postfix/main.cf
sail/tests/__init__.py
sail/tests/end2end.py
sail/tests/test_destroy.py
sail/tests/test_version.py
sailed_io-0.10.9.dist-info/entry_points.txt
sailed_io-0.10.9.dist-info/LICENSE
sailed_io-0.10.9.dist-info/WHEEL
sailed_io-0.10.9.dist-info/METADATA
sailed_io-0.10.9.dist-info/RECORD
