Metadata-Version: 2.1
Name: sailed.io
Version: 0.10.9
Summary: CLI tool to deploy and manage WordPress applications on DigitalOcean
Author-email: Konstantin Kovshenin <kovshenin@gmail.com>
Requires-Python: >=3.8
Requires-Dist: click==8.1.7
Requires-Dist: cryptography==43.0.1
Requires-Dist: decorator==5.1.1
Requires-Dist: fabric==3.2.2
Requires-Dist: invoke==2.2.0
Requires-Dist: Jinja2==3.1.4
Requires-Dist: packaging==24.1
Requires-Dist: paramiko==3.4.0
Requires-Dist: python-digitalocean==1.17.0
Requires-Dist: PyYAML==6.0.1
Requires-Dist: requests==2.32.3
Requires-Dist: tldextract==5.1.2
Project-URL: Homepage, https://sailed.io
